{
"meta":{"test_sets":[],"test_metrics":[],"learn_metrics":[{"best_value":"Min","name":"Logloss"}],"launch_mode":"Train","parameters":"","iteration_count":100,"learn_sets":["learn"],"name":"experiment"},
"iterations":[
{"learn":[0.6480896315],"iteration":0,"passed_time":0.001122794255,"remaining_time":0.1111566313},
{"learn":[0.6138548005],"iteration":1,"passed_time":0.002671963793,"remaining_time":0.1309262259},
{"learn":[0.5914905415],"iteration":2,"passed_time":0.004709163614,"remaining_time":0.1522629568},
{"learn":[0.5667772709],"iteration":3,"passed_time":0.006742796782,"remaining_time":0.1618271228},
{"learn":[0.5439539053],"iteration":4,"passed_time":0.008907354152,"remaining_time":0.1692397289},
{"learn":[0.5254670867],"iteration":5,"passed_time":0.0109744297,"remaining_time":0.1719327319},
{"learn":[0.506875646],"iteration":6,"passed_time":0.01282138953,"remaining_time":0.170341318},
{"learn":[0.4875482091],"iteration":7,"passed_time":0.01341781715,"remaining_time":0.1543048972},
{"learn":[0.4730102844],"iteration":8,"passed_time":0.01522504286,"remaining_time":0.1539421001},
{"learn":[0.4596836353],"iteration":9,"passed_time":0.01719015793,"remaining_time":0.1547114213},
{"learn":[0.4498700741],"iteration":10,"passed_time":0.01895059759,"remaining_time":0.1533275623},
{"learn":[0.4362648625],"iteration":11,"passed_time":0.01959930697,"remaining_time":0.1437282511},
{"learn":[0.4254231279],"iteration":12,"passed_time":0.02137737831,"remaining_time":0.1430639933},
{"learn":[0.416448658],"iteration":13,"passed_time":0.02311442859,"remaining_time":0.1419886327},
{"learn":[0.4078542261],"iteration":14,"passed_time":0.02476834835,"remaining_time":0.140353974},
{"learn":[0.3993227071],"iteration":15,"passed_time":0.02511849145,"remaining_time":0.1318720801},
{"learn":[0.391749587],"iteration":16,"passed_time":0.02700715421,"remaining_time":0.1318584588},
{"learn":[0.3845165983],"iteration":17,"passed_time":0.0287007832,"remaining_time":0.1307480124},
{"learn":[0.3775712857],"iteration":18,"passed_time":0.03067552653,"remaining_time":0.1307746131},
{"learn":[0.3718388329],"iteration":19,"passed_time":0.03254915124,"remaining_time":0.130196605},
{"learn":[0.3654947335],"iteration":20,"passed_time":0.03439075138,"remaining_time":0.1293747314},
{"learn":[0.3603266447],"iteration":21,"passed_time":0.03630790213,"remaining_time":0.1287280166},
{"learn":[0.3541013882],"iteration":22,"passed_time":0.03829174242,"remaining_time":0.1281940942},
{"learn":[0.3492496708],"iteration":23,"passed_time":0.0402625733,"remaining_time":0.1274981488},
{"learn":[0.3446232809],"iteration":24,"passed_time":0.04233068593,"remaining_time":0.1269920578},
{"learn":[0.3398657684],"iteration":25,"passed_time":0.04401015851,"remaining_time":0.1252596819},
{"learn":[0.3350986903],"iteration":26,"passed_time":0.04613455613,"remaining_time":0.1247341703},
{"learn":[0.330690238],"iteration":27,"passed_time":0.04802057882,"remaining_time":0.1234814884},
{"learn":[0.3269929659],"iteration":28,"passed_time":0.04995728119,"remaining_time":0.1223092057},
{"learn":[0.3230167824],"iteration":29,"passed_time":0.05214083399,"remaining_time":0.121661946},
{"learn":[0.3193797418],"iteration":30,"passed_time":0.05383067591,"remaining_time":0.1198166657},
{"learn":[0.3156483007],"iteration":31,"passed_time":0.0556762984,"remaining_time":0.1183121341},
{"learn":[0.3122010361],"iteration":32,"passed_time":0.05738720476,"remaining_time":0.1165134157},
{"learn":[0.3094047586],"iteration":33,"passed_time":0.05814641085,"remaining_time":0.1128724446},
{"learn":[0.3064840437],"iteration":34,"passed_time":0.06002901717,"remaining_time":0.1114824605},
{"learn":[0.3028684499],"iteration":35,"passed_time":0.06206151822,"remaining_time":0.110331588},
{"learn":[0.2996448719],"iteration":36,"passed_time":0.06372214049,"remaining_time":0.1084998608},
{"learn":[0.2961991416],"iteration":37,"passed_time":0.06568724098,"remaining_time":0.1071739195},
{"learn":[0.2939073156],"iteration":38,"passed_time":0.06746205595,"remaining_time":0.1055175747},
{"learn":[0.2912728137],"iteration":39,"passed_time":0.06925866732,"remaining_time":0.103888001},
{"learn":[0.2890245991],"iteration":40,"passed_time":0.07141275546,"remaining_time":0.1027646969},
{"learn":[0.286142007],"iteration":41,"passed_time":0.07353428227,"remaining_time":0.1015473422},
{"learn":[0.2834963417],"iteration":42,"passed_time":0.07547776183,"remaining_time":0.1000519168},
{"learn":[0.281226654],"iteration":43,"passed_time":0.07735361586,"remaining_time":0.09845005654},
{"learn":[0.2783347054],"iteration":44,"passed_time":0.07908543608,"remaining_time":0.09665997743},
{"learn":[0.2757465017],"iteration":45,"passed_time":0.08105048131,"remaining_time":0.09514621719},
{"learn":[0.2735466028],"iteration":46,"passed_time":0.08283595676,"remaining_time":0.09341075976},
{"learn":[0.2714878013],"iteration":47,"passed_time":0.0846159268,"remaining_time":0.09166725403},
{"learn":[0.2693570742],"iteration":48,"passed_time":0.08518088056,"remaining_time":0.08865765119},
{"learn":[0.2666328572],"iteration":49,"passed_time":0.08699364175,"remaining_time":0.08699364175},
{"learn":[0.2652059875],"iteration":50,"passed_time":0.08882693609,"remaining_time":0.08534352683},
{"learn":[0.2632954248],"iteration":51,"passed_time":0.09108806875,"remaining_time":0.08408129423},
{"learn":[0.2611832134],"iteration":52,"passed_time":0.09327889511,"remaining_time":0.0827190202},
{"learn":[0.2596460884],"iteration":53,"passed_time":0.09500368222,"remaining_time":0.08092906263},
{"learn":[0.2575444541],"iteration":54,"passed_time":0.09684821753,"remaining_time":0.0792394507},
{"learn":[0.2557832536],"iteration":55,"passed_time":0.09838150744,"remaining_time":0.07729975585},
{"learn":[0.2535369596],"iteration":56,"passed_time":0.1000970822,"remaining_time":0.07551183395},
{"learn":[0.2515246854],"iteration":57,"passed_time":0.1017348822,"remaining_time":0.07367008712},
{"learn":[0.2497543931],"iteration":58,"passed_time":0.1049912615,"remaining_time":0.0729600292},
{"learn":[0.2477944846],"iteration":59,"passed_time":0.107185364,"remaining_time":0.07145690934},
{"learn":[0.2458195603],"iteration":60,"passed_time":0.1089598086,"remaining_time":0.06966282844},
{"learn":[0.2442296795],"iteration":61,"passed_time":0.1109298534,"remaining_time":0.06798926501},
{"learn":[0.2423242063],"iteration":62,"passed_time":0.1128855807,"remaining_time":0.06629788072},
{"learn":[0.240751711],"iteration":63,"passed_time":0.1146933826,"remaining_time":0.06451502773},
{"learn":[0.2389085799],"iteration":64,"passed_time":0.1165237266,"remaining_time":0.06274354511},
{"learn":[0.2370165993],"iteration":65,"passed_time":0.1183455201,"remaining_time":0.060965874},
{"learn":[0.2356137397],"iteration":66,"passed_time":0.1199349599,"remaining_time":0.05907244295},
{"learn":[0.2336410835],"iteration":67,"passed_time":0.1216176837,"remaining_time":0.05723185116},
{"learn":[0.232112494],"iteration":68,"passed_time":0.1232112758,"remaining_time":0.05535579058},
{"learn":[0.2305307856],"iteration":69,"passed_time":0.125173476,"remaining_time":0.05364577545},
{"learn":[0.2290700019],"iteration":70,"passed_time":0.1267158174,"remaining_time":0.05175716485},
{"learn":[0.2271845775],"iteration":71,"passed_time":0.1284992342,"remaining_time":0.04997192439},
{"learn":[0.2258397046],"iteration":72,"passed_time":0.1300988025,"remaining_time":0.04811873519},
{"learn":[0.2247705386],"iteration":73,"passed_time":0.131789456,"remaining_time":0.04630440345},
{"learn":[0.2231958418],"iteration":74,"passed_time":0.1334280374,"remaining_time":0.04447601248},
{"learn":[0.2215767127],"iteration":75,"passed_time":0.1353388564,"remaining_time":0.04273858623},
{"learn":[0.2201287575],"iteration":76,"passed_time":0.1370954729,"remaining_time":0.04095059579},
{"learn":[0.2185557161],"iteration":77,"passed_time":0.1386703303,"remaining_time":0.03911214445},
{"learn":[0.2169873717],"iteration":78,"passed_time":0.1403597964,"remaining_time":0.03731083195},
{"learn":[0.2150811061],"iteration":79,"passed_time":0.1419860597,"remaining_time":0.03549651493},
{"learn":[0.2131954704],"iteration":80,"passed_time":0.1436027604,"remaining_time":0.03368459811},
{"learn":[0.2121123161],"iteration":81,"passed_time":0.1451527666,"remaining_time":0.03186280243},
{"learn":[0.2102394597],"iteration":82,"passed_time":0.1468593698,"remaining_time":0.03007962996},
{"learn":[0.2084566913],"iteration":83,"passed_time":0.148559,"remaining_time":0.02829695238},
{"learn":[0.2071229136],"iteration":84,"passed_time":0.1503553603,"remaining_time":0.02653329887},
{"learn":[0.2055087953],"iteration":85,"passed_time":0.151973078,"remaining_time":0.02473980339},
{"learn":[0.2040466155],"iteration":86,"passed_time":0.1536628045,"remaining_time":0.02296110872},
{"learn":[0.2026409848],"iteration":87,"passed_time":0.155467481,"remaining_time":0.02120011104},
{"learn":[0.2013913037],"iteration":88,"passed_time":0.1572363652,"remaining_time":0.01943370805},
{"learn":[0.2006203802],"iteration":89,"passed_time":0.1588205248,"remaining_time":0.01764672498},
{"learn":[0.1996261135],"iteration":90,"passed_time":0.1604800954,"remaining_time":0.01587165779},
{"learn":[0.1989020951],"iteration":91,"passed_time":0.1621135121,"remaining_time":0.01409682714},
{"learn":[0.1973291796],"iteration":92,"passed_time":0.1639130687,"remaining_time":0.0123375428},
{"learn":[0.1968799956],"iteration":93,"passed_time":0.1656653064,"remaining_time":0.01057438126},
{"learn":[0.1960543586],"iteration":94,"passed_time":0.1673421446,"remaining_time":0.008807481296},
{"learn":[0.1946990202],"iteration":95,"passed_time":0.1690078036,"remaining_time":0.007041991815},
{"learn":[0.1933416182],"iteration":96,"passed_time":0.1706992527,"remaining_time":0.005279358332},
{"learn":[0.1924233711],"iteration":97,"passed_time":0.1724019137,"remaining_time":0.003518406402},
{"learn":[0.1923254675],"iteration":98,"passed_time":0.1740357512,"remaining_time":0.001757936881},
{"learn":[0.1913025522],"iteration":99,"passed_time":0.1758989313,"remaining_time":0}
]}